windroselab/__init__.py
windroselab/app_context.py
windroselab/call_buttons.py
windroselab/depictFunc.py
windroselab/display.py
windroselab/draw_class.py
windroselab/fall.py
windroselab/gui.py
windroselab/opener.py
windroselab/seasons.py
windroselab/spring.py
windroselab/summer.py
windroselab/winter.py
windroselab-0.1.5.dist-info/licenses/LICENSE
windroselab-0.1.5.dist-info/METADATA
windroselab-0.1.5.dist-info/WHEEL
windroselab-0.1.5.dist-info/top_level.txt
windroselab-0.1.5.dist-info/RECORD
